ShrtCde/IO.py
ShrtCde/UI.py
ShrtCde/__init__.py
ShrtCde-0.4.8.dist-info/LICENSE
ShrtCde-0.4.8.dist-info/METADATA
ShrtCde-0.4.8.dist-info/WHEEL
ShrtCde-0.4.8.dist-info/top_level.txt
ShrtCde-0.4.8.dist-info/RECORD
