Metadata-Version: 2.1
Name: ShrtCde
Version: 0.4.8
Summary: Helps shorten the amount of code you write
Home-page: https://github.com/Uralstech/ShrtCde
Author: Uralstech (Udayshankar Ravikumar)
Author-email: <info@uralstech.in>
License: Apache License 2.0
Keywords: python,shrt,short,cde,code,shortcode,shrtcde,ui,sort,file,io,library
Classifier: Development Status :: 3 - Alpha
Classifier: Intended Audience :: Developers
Classifier: Programming Language :: Python :: 3
Classifier: Operating System :: Unix
Classifier: Operating System :: MacOS :: MacOS X
Classifier: Operating System :: Microsoft :: Windows
License-File: LICENSE
